{"curContainerId":"ffc1b577-37bb-da28-8c56-8267fd80757b","version":"3.4.0","containers":[{"__class":"Container","__uniqueId":"ffc1b577-37bb-da28-8c56-8267fd80757b","graph":{"__class":"ScriptGraph","__uniqueId":"06366b8e-7bd2-254a-3de3-7916475e5989","panelName":"Visual Scripting","graphType":"SCRIPT","editable":true,"transform":{"a":1,"b":0,"c":0,"d":1,"e":-49703,"f":-49414},"transformLocal":{"a":1,"b":0,"c":0,"d":1,"e":-50000,"f":-50000},"scaleTransformLocal":{"a":1,"b":0,"c":0,"d":1,"e":0,"f":0},"nodeList":[{"__class":"ScriptTemplateNode","__uniqueId":"af86c0dd-8646-7110-9f8a-708aaf6d13cb","nodeType":"SCRIPT","position":{"x":50266.5,"y":50073},"name":"Update","owner":{"__referenceId":"06366b8e-7bd2-254a-3de3-7916475e5989"},"size":{"width":164,"height":92},"description":"Execute the next node in every frame.","category":"Event","deletable":true,"cloneable":true,"inputPorts":[],"outputPorts":[{"__class":"ScriptPort","__uniqueId":"33f1693b-96e4-5899-b21b-3b64bf3dfef8","portName":"Next","type":"CONTROL","isInput":false,"isConnected":false,"isDynamic":false,"centerPosition":{"x":50416.5,"y":50121},"valueTypeName":"Pulse","portIndex":0,"portValue":null,"visible":true,"refEdges":[],"owner":{"__referenceId":"af86c0dd-8646-7110-9f8a-708aaf6d13cb"},"hideInput":false,"isArray":false,"singleValueType":"Default","generic":null,"valueList":[],"valueListKeys":[],"defaultDisplayName":"Next","defaultDisplayType":"Exec","defaultValueList":[],"addManually":false},{"__class":"ScriptPort","__uniqueId":"cc292bf6-13d7-5ba5-4be4-20ced9775a8c","portName":"Delta Time","type":"DATA","isInput":false,"isConnected":false,"isDynamic":false,"centerPosition":{"x":50416.5,"y":50145},"valueTypeName":"Double","portIndex":1,"portValue":null,"visible":true,"refEdges":[],"owner":{"__referenceId":"af86c0dd-8646-7110-9f8a-708aaf6d13cb"},"hideInput":false,"isArray":false,"singleValueType":"Default","generic":null,"valueList":[],"valueListKeys":[],"defaultDisplayName":"Delta Time","defaultDisplayType":"Number","defaultValueList":[],"addManually":false}],"error":false,"groupEnable":true,"renamable":false,"nodeSettings":[],"defaultDisplayName":"Update","nodeName":"","templateGuid":"76dd06cb-6f7a-60eb-e2fa-c9b10a0c78fc","curSelectedType":"","containResource":false,"version":"1.0.1","compatibleState":0,"addableInputConfig":null,"addableOutputConfig":null,"portAddable":0},{"__class":"ScriptTemplateNode","__uniqueId":"51fad0ec-0094-c900-1736-60b3f0a0ed4e","nodeType":"SCRIPT","position":{"x":50266.5,"y":50223},"name":"Start","owner":{"__referenceId":"06366b8e-7bd2-254a-3de3-7916475e5989"},"size":{"width":164,"height":84},"description":"Execute the next node when an effect starts.","category":"Event","deletable":true,"cloneable":true,"inputPorts":[],"outputPorts":[{"__class":"ScriptPort","__uniqueId":"5ec57450-94bf-cfc9-5a65-4e62a115cff8","portName":"Next","type":"CONTROL","isInput":false,"isConnected":false,"isDynamic":false,"centerPosition":{"x":50416.5,"y":50271},"valueTypeName":"Pulse","portIndex":0,"portValue":null,"visible":true,"refEdges":[],"owner":{"__referenceId":"51fad0ec-0094-c900-1736-60b3f0a0ed4e"},"hideInput":false,"isArray":false,"singleValueType":"Default","generic":null,"valueList":[],"valueListKeys":[],"defaultDisplayName":"Next","defaultDisplayType":"Exec","defaultValueList":[],"addManually":false}],"error":false,"groupEnable":true,"renamable":false,"nodeSettings":[],"defaultDisplayName":"Start","nodeName":"","templateGuid":"2f0fed0f-5279-9602-3083-5e1fb8163563","curSelectedType":"","containResource":false,"version":"1.0.1","compatibleState":0,"addableInputConfig":null,"addableOutputConfig":null,"portAddable":0}],"edgeList":[],"owner":{"__referenceId":"ffc1b577-37bb-da28-8c56-8267fd80757b"},"showMiniMap":false,"variableList":[],"localVariableList":[],"showVariablePanel":false,"showSubGraphPanel":false},"parent":null,"root":{"__referenceId":"ffc1b577-37bb-da28-8c56-8267fd80757b"},"title":"Main Graph","subContainerManager":{"__class":"SubContainerManager","__uniqueId":"64cb2c77-df2b-72db-af2b-ba0d7345f3ca","owner":{"__referenceId":"ffc1b577-37bb-da28-8c56-8267fd80757b"},"subContainers":[]},"containerType":0}],"panelClosed":false,"panelCollapsed":false,"minimapOpen":false}